flask_basicauth_ldap.py
Flask_BasicAuth_LDAP-0.0.0a1.dev2.dist-info/METADATA
Flask_BasicAuth_LDAP-0.0.0a1.dev2.dist-info/RECORD
Flask_BasicAuth_LDAP-0.0.0a1.dev2.dist-info/WHEEL
Flask_BasicAuth_LDAP-0.0.0a1.dev2.dist-info/top_level.txt
