Metadata-Version: 2.1
Name: Flask-BasicAuth-LDAP
Version: 0.0.0a1.dev2
Summary: Flask extension that provides an easy way to protect certain views of an application with LDAP and HTTP basic access authentication.
Home-page: https://github.com/ArtemAngelchev/flask-basicauth-ldap
Author: Angelchev Artem
Author-email: artangelchev@gmail.com
License: MIT
Keywords: ldap,flask,api,rest,auth,basicauth
Platform: UNKNOWN
Classifier: Intended Audience :: Developers
Classifier: Programming Language :: Python :: 3.6
Classifier: Programming Language :: Python :: 3.7
Classifier: Programming Language :: Python :: 3 :: Only
Requires-Dist: Flask (>=0.10)
Requires-Dist: ldap3
